{
  "indexes": [
    {
      "collectionGroup": "jobs",
      "queryScope": "COLLECTION",
      "fields": [
        { "fieldPath": "companyId", "order": "ASCENDING" },
        { "fieldPath": "status", "order": "ASCENDING" },
        { "fieldPath": "updatedAt", "order": "DESCENDING" }
      ]
    },
    {
      "collectionGroup": "jobs",
      "queryScope": "COLLECTION",
      "fields": [
        { "fieldPath": "companyId", "order": "ASCENDING" },
        { "fieldPath": "assignedToUserId", "order": "ASCENDING" },
        { "fieldPath": "updatedAt", "order": "DESCENDING" }
      ]
    },
    {
      "collectionGroup": "jobs",
      "queryScope": "COLLECTION",
      "fields": [
        { "fieldPath": "companyId", "order": "ASCENDING" },
        { "fieldPath": "updatedAt", "order": "DESCENDING" }
      ]
    },
    {
      "collectionGroup": "invoices",
      "queryScope": "COLLECTION",
      "fields": [
        { "fieldPath": "companyId", "order": "ASCENDING" },
        { "fieldPath": "status", "order": "ASCENDING" },
        { "fieldPath": "createdAt", "order": "DESCENDING" }
      ]
    },
    {
      "collectionGroup": "invoices",
      "queryScope": "COLLECTION",
      "fields": [
        { "fieldPath": "companyId", "order": "ASCENDING" },
        { "fieldPath": "createdAt", "order": "DESCENDING" }
      ]
    },
    {
      "collectionGroup": "invoices",
      "queryScope": "COLLECTION",
      "fields": [
        { "fieldPath": "companyId", "order": "ASCENDING" },
        { "fieldPath": "updatedAt", "order": "DESCENDING" }
      ]
    },
    {
      "collectionGroup": "customers",
      "queryScope": "COLLECTION",
      "fields": [
        { "fieldPath": "companyId", "order": "ASCENDING" },
        { "fieldPath": "name", "order": "ASCENDING" }
      ]
    },
    {
      "collectionGroup": "customers",
      "queryScope": "COLLECTION",
      "fields": [
        { "fieldPath": "companyId", "order": "ASCENDING" },
        { "fieldPath": "updatedAt", "order": "DESCENDING" }
      ]
    },
    {
      "collectionGroup": "users",
      "queryScope": "COLLECTION",
      "fields": [
        { "fieldPath": "companyId", "order": "ASCENDING" },
        { "fieldPath": "status", "order": "ASCENDING" }
      ]
    },
    {
      "collectionGroup": "auditLogs",
      "queryScope": "COLLECTION",
      "fields": [
        { "fieldPath": "companyId", "order": "ASCENDING" },
        { "fieldPath": "createdAt", "order": "DESCENDING" }
      ]
    },
    {
      "collectionGroup": "examProgress",
      "queryScope": "COLLECTION",
      "fields": [
        { "fieldPath": "updatedAt", "order": "DESCENDING" }
      ]
    }
  ],
  "fieldOverrides": []
}
